{
  "id": "do-ley-263-adicion-de-un-parrafo-al-art-1",
  "type": "statute",
  "title": "ADICION DE UN PARRAFO AL ART. 12 DE LA LEY N° 17, DEL 12 DE NOVIEMBRE DE 1930 SOBRE RETIRO DE LAS FU...",
  "title_en": "ADICION DE UN PARRAFO AL ART. 12 DE LA LEY N° 17, DEL 12 DE NOVIEMBRE DE 1930 SOBRE RETIRO DE LAS FU...",
  "short_name": "Ley No. 263",
  "status": "in_force",
  "issued_date": "1940-05-06",
  "in_force_date": "1940-05-06",
  "url": "https://www.consultoria.gov.do/Consulta/Home/FileManagement?documentId=3274035&managementType=1",
  "provisions": [
    {
      "provision_ref": "parrafo-unico",
      "section": "ADICION DE UN PARRAFO AL ART. 12 DE LA LEY N° 17, DEL 12 DE NOVIEMBRE DE 1930 SOBRE RETIRO DE LAS FU...",
      "title": "En 10s casos de inutilidad fisica contraida en",
      "content": "PARRAFO: En 10s casos de inutilidad fisica contraida en\nel servicio que, conforme a1 dictamen de la Junta M6dica dei\n-136-\nEjercii 0, no incapacite absolutamente para trabajos que no\nSean militares, el retiro forzoso se dispondrk con una pensi61.1\ntemporal cuya cuantia y duraci6n s e r h fijadas por dicha Jlu’n-\nta y recomendadas a la consideracih del Presidente de la ;Re.\np6b1ic.s .\nUADA en la Sala de Sesiones del Senado, en Ciudad T w -\njillo, distrito de Santo Domingo, ICapital de la Reptiblica Do-\nminicsna, a 10s veintinueve dias del mes de abril del ago mil\nnoveLientos cuarenta; afio 970 de la Independencia, 779 de la\nRestauraci6n 1- 100 de la “Era de Trujillo”.\nEl Presidente,\nPorfirio Herrera.\nLos Secretarios:\nDr. Josk E. kybar.\nSantiago Rodriguez.\nDADA en la sala de sesiones de la CQmara de [Diputadoa,\nen Ciudad Trujillo, Distrito de Santo Domingo, Capital de la\nRepcblica Dominicana, a 10s dos dias del mes de Mayo del afio\nmil novecientos cuarenta; afio 970 de la Independencia, 779 dt‘\nla Restauracih y 100 de la “Era de Trujillo”.\nEl Presidente,\nA. Pellerano Sardh.\nLos Secretarios :\nLuis SQnchez A.\nAIej. Amable Nadal.\nM. DE J. TRONCWO DE LA CONCHA,\nPresidente de Ia Repiiblica Dominicana.\nEn ejercicio de la atribucidn que me confiere el articulo\ntrejniisiete de la Constitucih del Estado,\nPROMULlGIO la presente ley, y mando que sea publicada\nen la Gaceta Oficial para su conocimiento y cumplimiento.\nDADA en Ciudad Trujillo, ,Distrito de Santo Domingo, C d -\npita1 de la Bepiiblica Dominicana, a 10s 6 dias del mes de mayo\ndel aiio mil novecientos cuarenta, aiio 970 de la Independencia,\n770 dz la Restauraci6n y 100 de la “Era de Trujillo”.\nM. DE J. TRONlCOSO DE LA CONCHA."
    }
  ],
  "definitions": []
}