{
  "id": "do-ley-986-aprobacion-de-resolucion-del-a",
  "type": "statute",
  "title": "APROBACION DE RESOLUCION DEL AYUNTAMIENTO DE CASTILLO QUE DONA AL CLUB \"16 DE AGOSTO\"",
  "title_en": "APROBACION DE RESOLUCION DEL AYUNTAMIENTO DE CASTILLO QUE DONA AL CLUB \"16 DE AGOSTO\"",
  "short_name": "Ley No. 986",
  "status": "in_force",
  "issued_date": "1935-09-14",
  "in_force_date": "1935-09-14",
  "url": "https://www.consultoria.gov.do/Consulta/Home/FileManagement?documentId=3269173&managementType=1",
  "provisions": [
    {
      "provision_ref": "full-text",
      "section": "APROBACION DE RESOLUCION DEL AYUNTAMIENTO DE CASTILLO QUE DONA AL CLUB \"16 DE AGOSTO\"",
      "title": "APROBACION DE RESOLUCION DEL AYUNTAMIENTO DE CASTILLO QUE DONA AL CLUB \"16 DE AGOSTO\"",
      "content": "CONSIDERANDO : Que las Ayunitamientos’ deben estimu-\nl a r y hasta promover, o coolperar en toda obra que propenda a1\ndesarrollo de la cultura, corn0 primer enunciado de progreso,\ny que .el Cluh “16 de Agosto” Inc. se orienta en esa finalidad,\n       IEnuso de las facultades que le confiere la Ley,\n                        R E S U E L V E :\n       1.- Enajenar a titulo gratuito a favor del Club “16 de\nAgoisto” I n c la casa que ocupa dicho cenbro en eslta pdbl’acih,    *\ncaile “General Tenallas”, reservbndose el derecho de propiedad\nen caso de disoloci6n del Club.\n       2.- Enviar la presknte Resoluci6n a la Honorable Cbmara\nd2 Dilputados, para 10s fines de su ‘aprobaci6n.\n       DADA en la Sala de Sesiones del Ayuntamiento de la Comdn\nde Castillo, a 10s 22 dials del mes de Junio del aiio 1935 .- ADOL\nF O GARCIA M., Presidente del Ayuntamiento.-                RAFAEL\nMARTE, Secretario” .\n       DADA en la lSala de Sesiones de la CBmam de Diputdos en\nSanto Dbmingo, D. N . , Repdblica Daminicana, a 10s once dias’\n del mes de Septiembre del @a mil novecientols treinta y cinco;\naiio 9D de la Independsm5a y 739 de la Restauraci6n.\n                                         El Presidents,\n                                      Miguel &geI Roc&.\nLos Secretarios :\n    J. M. Vidal V.\n    Dr. Jose E. Aybar.\n    Publiquese y camuniquese   .                                     (P\n\n                                      -337-\n.is\n           DADA en la Mansidn Presidencial, en la ciudad de Santo\n      Domingo, Capital de la ,Re;pdblica ,Dominicans, a 10s catorce\n      dim del mes de setiembre del aiio mil novecientod treinta .v\n      cinco .\n                                   RAFAEL L. TRUJILLO.\n\n      Auhri-ih   para la Circulacitjn de sellos cenmamor I t h s del Descubri-\n         miento & Aw&ka.- G. 0. No. 4852, del 18 de S a p t i e d m de 193.5.\n                         EL CONGRESO NACIONAL,\n                          En Nombre de la Repliblica\n       NUMIEXW 987.\n             VI8TA la exposiei6n dirjgida d Poder Ejecutivo en fecha\n       treirtki y una de enero del aiio corriente ipor el seiior Nicolhs\n       Rivero, Conde del Rivero, I?residente de la Sociedd Colomlbista\n       Panamericana con sede en la ciludad de La Habana, en la cual\n       solkita del Gobierno Dorminicano que el dia doce de octubre de\n       cada afio, a partir del mil novecienltols treinta y cinco, como un\n       hmenaje a Cristbbal Colh, Descubridor de AmAriw, conceda\n       vigencia y ponga en dmulacibn postal uno o varios sallos que\n       con retratas' y alegorias referentes a1 Descubridor editarii por\n       su cuenta y Tiesgo la Sacidad Calombista Panamericana, con\n       el fin de mantener vivos en la memoria del mundo las figuras,\n       lugares y simbralos que consltiltuyen la Wopeya de la civilizaci6n\n      del Nuevo Mundo.\n            CONSIDERANDO que la Socialad Colombista Panameri-\n      cana, instituci6n intmemacional de cultura, cuepta con la coope-\n      raci6n de las' naciones americanas con territorios descubiertos\n      por Cristhbal Coldn para el homenaje priridico y anual que se\n      pmpone rendir a1 Descubridor del N u w o Mundo v sus colabo-\n       rdores, pnimndo en ciltculaci6n ,posltai uno o varios tsellos con-\n      memorativos del bisthrico S U C ~ S Odel Descubrimieiito ;\n            ClONSIDE*RANDOque la Reptiblica Dolminicana. e jercs su\n       s'oberania en uno de lm territorios descuhiertm por Cristhbal\n      Col6n; que en (tierras de la I d a de Santo Domingo pertmscien-\n      tes ahora a la Repfiblica Dominitcana se fund6 por Crist6bal Co-\n      1611 la Iubela, primera ciudad cristiana ,del Nuevo Mundo; q u a\n      en tien'as de Santo Domingo, bajjo el mando de Cristbbal Co-\na     16n, Virrey de las India's, s? levantaron lot$ primeros establsi-\n      mientos de e8paiioles en America; que la ciudad de Santo Do-"
    }
  ],
  "definitions": []
}