{
  "id": "do-ley-325-autoriza-al-podera-ejecutivo-a",
  "type": "statute",
  "title": "AUTORIZA AL PODERA EJECUTIVO A EXONERAR DEL PAGO DE DERECHOS DE PATENTES",
  "title_en": "AUTORIZA AL PODERA EJECUTIVO A EXONERAR DEL PAGO DE DERECHOS DE PATENTES",
  "short_name": "Ley No. 325",
  "status": "in_force",
  "issued_date": "1932-04-21",
  "in_force_date": "1932-04-21",
  "url": "https://www.consultoria.gov.do/Consulta/Home/FileManagement?documentId=3358845&managementType=1",
  "provisions": [
    {
      "provision_ref": "full-text",
      "section": "AUTORIZA AL PODERA EJECUTIVO A EXONERAR DEL PAGO DE DERECHOS DE PATENTES",
      "title": "AUTORIZA AL PODERA EJECUTIVO A EXONERAR DEL PAGO DE DERECHOS DE PATENTES",
      "content": "EL CONGRESO NACIONAL,\n                  En Nombre de la Rep6blica.\n                HA DADO LA SIGUIENTE LEY:\n\n     ART. UMC0:- El Poder Ejwutivo queda autorizado para\nexonerar de1:pago d,e derechos de Patentes comprendidos en la\nLey No. 67, de fech~a9 de Diciemlbre del afio 1930, y sus enmien-            t\n\ndm, a la6 personas establecidas en 10s ramos de Farmacias, Bo-\ndegas y Carniceriw, dentro de las Cdonias Agricolas del Esta-\ndo situadas en la linea fronkriza, siernpne que 10s exonerados\nprooedrun de acuerdo con las reglsrmenb.ciones de la Secretaria de\nEstado & Agricu1,tura y Comercio y soliciten de didha Secretaria\nde Estado sus respectivas exoneraciones.\n     Dada en .la Sala dfe Sesiones del Palacio &el Senado, en San:\nto h m i n g o , Capital de la Reppbblica Dlominicana, a 10s t r w &as\ndel m a de Abril del a f ~ omil novecientoe trzintidos, aiios 890. de\nla In&pendencia y 690. de k Resburaci6n.\n                                            El Presidente :\n                                        Mario Fermin Cabral.\n\n                                                                         '\n     Dsda e n la Sala de Seaiones de la m m a r a de Diputsdos, en\nSanto Ibmingo, &pita de la Rep6blica Dominicans, a 10s dieci-\nn m e &fa# del mes de Abril del aiio mil novecienbs treintidoe,\na h 890. de la Independencia y 690. de la ELestauraciOn.\n                                      El Presidente :\n                                   Miguel Angel Roca.\n\n     Ejectitme, comuniquese y publfquese en t d o el territorio\nde la Reptlblica, para su conocimiento y c u ~ l i m i e n t o .\n     Dab en el Palacio del Ejecutivo, en Santo D d n g o , CapiW\n\n                                      -1%-\n        ae la Repiiblica Dominicans a 10s veintiiin (21) dias del mee de\n\"bril         del aiio mil novecientos treinta y dos.\n                                         RAFAEL L. TRUJILLO,\n                                        Presidente de la Rephblica.\n        Refrendado :\n           Jacinto B. Peynado,\n        Secretario de Estado de la\n               Presidencia, Inkrino.\n                                               Refrendado :\n                                           Santiago Mich Aena hijo,\n                                        Secretario de Estado de Hacienda.\n        Ref rendado :\n                 C4sar Tol,entino,\n        Secretario dle Estadfo d,e Agricultura\n                   y Comercio.\n\n        NUMERO 326.\n            Ley q u e autoriza transferencia e n la Ley de Gastos Phblicos\n        (Gaceta Oficial No. 44-60 de fecha 27 de Abril de 1932).\n\n        XUMERO 327.\n            Ley que autoriza transfer.encila en la Ley dde Gastos Phblico3\n        (Gaceta Oficial No. 4460 de fecha 27 de Abril de 1932).\n\n           Ley que autwiza transferencia en la Ley de Gastos Phblims\n        (Gaceta Oficial No. 446.1 de fecha 30 de Abrii de 1932).\n                                             -\n                          EL CONGRESO NACIONAL,\n                          En Nombre de la Repliblica.\n                                    ---\n    *NUMERO329.\n          CONSIDERANDlO: qce 103 estudios przliminares sobre m\n     sistema cientifico de tributacidn han sido cornpletados par la Co-\n        misi6n Especial de I m p u ? s t ~ sbajo !a su~ervisi6ndirecta del Po-\n        der Ejecctivo y que se hace nz.cesario la formulni6n y adopcibn\n        dte un plan rentistico definitiv3;\n             CONSPCxERANDO: qu? para poder roner dicho plan en e'e-\n        cusi6a para el prciximo afio fiscal $2 1933, se necesita un pzriodo\n        previo de prsparacibn a fin dp, reorgankar y perfexionar el De-"
    }
  ],
  "definitions": []
}