{
  "id": "do-ley-722-autorizacion-al-presidente-de-",
  "type": "statute",
  "title": "AUTORIZACION AL PRESIDENTE DE LA REPUBLICA PARA DEPOSITAR EL INSTRUMENTO DE ADHESION DE ESTA AL TRAT...",
  "title_en": "AUTORIZACION AL PRESIDENTE DE LA REPUBLICA PARA DEPOSITAR EL INSTRUMENTO DE ADHESION DE ESTA AL TRAT...",
  "short_name": "Ley No. 722",
  "status": "in_force",
  "issued_date": "1934-07-18",
  "in_force_date": "1934-07-18",
  "url": "https://www.consultoria.gov.do/Consulta/Home/FileManagement?documentId=3268155&managementType=1",
  "provisions": [
    {
      "provision_ref": "art1",
      "section": "AUTORIZACION AL PRESIDENTE DE LA REPUBLICA PARA DEPOSITAR EL INSTRUMENTO DE ADHESION DE ESTA AL TRAT...",
      "title": "V.- Las Altas Partes Contratantes se cibli-",
      "content": "ARTICULO 1V.- Las Altas Partes Contratantes se cibli-\ngan a someter a1 procedimiento de conciliaeih creado por el\npresente Tratado, 10s conflictas mencionados especialknente .y\nr,uaksquiera otms que surjan en sus reiaciones reciprocas, sin\nmas limitaciones que las que se enumerm en el articulo siguien-\nte, en todas las controversias que no hayar, podido ser resutltas\npor la via diplomhtica dentro de un plazo razonable.\nARTECULO V.- Las Altas Partes Contrantantes p 10s Es-\ntados que en adelante se adhieran a1 presente Tratado, no po-\ndran formular en el momento d'e la firma, ratificaei6n o adhe-\nsi6n o h J limitaciones SI procedimiento de conccdiacihn que\ncualquiera de las que a continuacih se seiialan:\n(a)-Las diferencias para cuya soluci6n se hayan celebra-\ndo TraMos, Convenciones, Pactos o Acuerdos pacifisltas de\ncualquier indole qut. sean, que en ningtin cam se entenderhn de-\nrogados pvr el presente convenio, sino completadas en cuanto\n-133-\npropendan a asegurar la paz; R S ~como las cuestiones o asuntos\nresueltos por tratados anteriores.\n' (b)-    Los conflictos que las Partes prefieren resolver por\narreglo direct0 o som2tcr ctn comdn acuerdo a una soluci6n ar-\nbitral o judicial.\n(c)- Las cuestiones que el Derecho Internacional deja li-\nbradas a la campetencia exclusiva de cada Estado, de acuerdo\ncon su rbgimen constitucional, por cuyo motivo ias Partes po-\ndran opon2rse a qun Sean someti,das a1 procedimiento de conci-\nliacidn antes que la jurisdicci6n nacionai o local se haya pronun-\nciado en definitiva; salvo manifiesta denegacibn o re^^ d:\njustitia, en cuyo cas0 e1 traniite de la conciliaci6n deberh h i -\nciarse dentro del aiio a mas tasdar.\n(d) - Los asuntos que afeclten preceptos constitucionales\nde las Partes en controversia. En cas0 &e duda, cada Parte re-\ncabara la opini6n fun'dada de su respectivo Tribunal o C x t e\n1)\nSuprema de Justicia, si ksta estuviere investida de tales atrl-\nbuciones.\nLas Altas Partes Contratantes potirhn comunicar. en clnai-\nq u i a tiempo y en la forma establecida por ell articulo X'V, el\ninstrumento en que consc2 que han abandonado en todo i) en\np a t e las limitaciones por ellas establecidas a1 procedimiento\ncie conciliaci6n.\nLas limitaciones formuladas por una de las Partes Contra-\ntantes tendran el efecto de que las d e m b Partes no se conside-\nraran obligaidas a su respecto sino en la medida de las excepclo-\nnes establecidas.\nARTICULO VI.- A falta de Camisih PPrmanente de Con-\nciliaci6n o oe otro organismo internacional encargado de esta\nmisi6n en vintud de tratados anteriores en vigencia, las Aitas\nPartes Contratantes se comprmeten a someter sus diferencias\n*       a1 examen e investigacidn de una Comisi6n de Conciliacih que\nse formarii del siguiente modo, salvo acuerdo en contrario de\nlas Partes en c d a caso.\nL a C m i s i h de Canciliacih se compondra de cinco Miem-\nbros. C d a Park! en contraversia designara un miemhro que\npodra scr &gido por ella entre sus prqpios nacionales. Los\ntres miembros restantes seran designados tie cornun acuerdo\nwr las Partes entre 10s nacionales de terceras Pokncias que\ndeberan ser de nacionalidad diferente, no tener su residacia\nkgabitual en el territorio de las Partes interesadas ni estar al\nsefrvicio de ninguna de ellas. Entre dichos tres Miembros Ins\nPartes elegiran a1 Presildente de la Comisi6n de Conciliadjn.\nS i no pudieran ponerse de acuerdo sobre emas deesignacio-\nnes, podrhn encamlendadas a una terlcera Potencia o a cualquier\notro organismo internacional exis;tertte. S i 10s candidatos asi\ndesigllados no fueren acaptados por 1- Partes o por &una de\ndla, cada Parte presentara una lists de c a d i d a t a en nClaePo\n4   igud a1 de los mienJbros por e   -,     y is suerte deeidirii c W s\n-134-\ncandidatos deban integrar la Comisih de ConciliacMn.                     b\nARTICULO W1.- Los Tribunales o Cortes ~ U p W m 3de\nJusticia que, seghn la legislacih interna de cada Estado, ten-\nfan competencia para interpretar, en atim o dnica instancia\ny en 10s asuntos de su respeetiva jurisdicci6n, la ConstiQuci4h,\n10s tratados, o 10s principios generalles del Derecho de Gentes,\npodran ser designado8 con preferencia por las Altas Partes Con-\ntratantes para desempefiar las funciones encomenciadas por e:\npresenke Tratado a la Camisi6n de Conciliaci6n. En est? cas0 1.\nTribunal o Corte funcionarhn en pleno o designancio algunos de\nsus miembros para wtuar solos o formando Comisi6n mixta con\nmiembros de otras Ccrtes o Tribunales, seghn convengan de\ncomhn acueldo k s Partes en iitigio.\nARTICULO V I I .-  ~ La Comisi6n de Conciliacih esta61le-\nceriz por si misma las reglas de su procedimiento, el que de-\nber6 ser conteiicwso cn todos 10s ~ ~ S O S .\nLas Partes en controversia podran suministrar y la Coml-\nsi6n requerir d? ellas todo. lee antwcedentes e infomaciones nc-         i\ncesarias. Las Partes podrhn hacerse representar por delegados\ny asistir por consejeros o peritos, asi colmo tambi6n presmtar\ntoda clase d e testirnonios."
    },
    {
      "provision_ref": "art1",
      "section": "AUTORIZACION AL PRESIDENTE DE LA REPUBLICA PARA DEPOSITAR EL INSTRUMENTO DE ADHESION DE ESTA AL TRAT...",
      "title": "X.- Los trabajos y deliberaciones de la Co-",
      "content": "ARTICULO 1X.- Los trabajos y deliberaciones de la Co-\nmisi6n de Conciliacidn no se darirn a publicidad sino por deci-\nsi6n de la misma, con asentimiento de las Partes,\nA f d t a de estipulzuci6n en contrario, las decisiones de la\nComisi6n se adopkftn par mayoria de v&s, p r o la Cornisi6n\nno podmi expdrse sobre el fondo del asunto sin b presencitr de\ntodas SUB miembras.\nARTiCUW X.- Es misi6n de la Comisi6n pracurar el ave\nnimiento comiliahrio tie las diferencias sometidas a su conside-\nraci6n.\nDespuBs del estudio impancia1 de Ias cuestiones que Sean\nmateria del codPicto, m s i &       en un informe 10s resultsdos     ~\nde SUB tareas y pmpondrC1 a las Partes bases de arreglo median-\nte sduci6n justa y equitativa.\nEl iaforme de la Comisih en ningtin cas0 terwlra.ca,riictcr\nde sateocia ni de l a h b anbitrd, sea en lo concerniente a la ex-\nposici6n o in2Rnpretaci6n de 10s hedw, sea en lo relativo a laif\ncoxtsideraciones o conclusionas de dereaho.\nABTh(3W X      I:- La ComisSi6n de Conciiiaci6n deberii pre-\nmntar su in9orme, en d tkmino de un aiio contado &de su\nprimera reuni6n, a menos que las Partes no muelvan & CQ-\nmiin acuerdo abreviw o prorrogar ate p h .\nUna vez iniciado e~procedimiento de conciliacidn. ~ 6 1 0pa-\nd& Wmmmpime por arre;lo d ~ & entre hs Partes o pa- su\nikchith paeMor de someter de comiin acuerdo el conflicto*\nd rrbjhale o a la Wtiiia inbmwionai.\nAETXYtN& XU.- A1 c a u u n h su infmes las Partee,\nh camirldn de €hciiW6n Pee fi.jarS u!n tkrmho que na e.=-\n&.rh & &-,             dentro did cud MImmunciuae\nI            &e      &\n-1 35-\n$!\n12s bases del arreglo propueAo por la misma. Expirado este Pia-\n20, la Comisidn hara constar en un Acta final la decisih de las\nPartes.\nTranscurrido el plazo sin qu- las Partes hayan aceptado el\n:irreglo, ni adoptado de coni6n acuerd9 otra soluci6n amistosa,\n!as Parte5 en litigio recupeisran su libtrtad de acci6n para pro-\nceder como crean conveniente d2ntro da las limitaciones !!eri-\nvaclas c,e 10s articulos I y I1 del p r e s d e Tratado.\nARTICULO XII1.- Desd- la iniciacibn del procedimiento\nconciliatorio hasta la expiracion dol plazo fijado por la Comi\nsi617 para que las Partes se pronumien, deberan abstenerse de\ntoda medida perjudicial a la ejecucibn, del arreglo que propon-\nga la Comisih y, en general, todo azto susceptible ds agravar\no prolongar la controversia.\nARTTfuLO XIv .- Durante el prosedimiento d: concilia-\ncibn los miembros d. la Comisi6n percibiran honorarios C U ~ O\n0        monto serB establecido de com6n acuer6o por las P a r k s en mu-\ntroversia. Cada una de ellas proveer; a ws propios gastos y ,\nFor partes iguales, s d r a g a r a 10s gastos u honorarios comuned.\nARTICULO XV - El presente Trataldo sera ratificaco por\nlas Altas P a r t s Contratantes a la br2vedad posible, de aeuer-\ndo con sus roegectivos procedimientos constitucionales.\nEl Tratado original y 10s instrumentos de ratificacibn se-\nr6n depositados en el nlinisterio de Rdacionts Exteriores y CU!-\nt o de la Repiiolica Argentina, el cual comunicara ias ratificario-\nr,es a 10s dem5s Estados signatarios. E1 Tratado entrara en vigor\nentre las Altas Partes Contratantes treinta dias despuk; d d\ndepbsito d2 las respectivas ratificaciones, y en ~1 orden en que\nW a s se sfcct6en.\nARTBCULO XV1.- Este Tratado queda abierto a la adhe-\n3   si6n de todos 10s Estado-s.\nLa adhesi6n se harh mediante el dep6sito del respectivo\nh t r u m e n t o en el Ministerio de Relaciones Exteriores y C d t c\nde la Republica Argentina, el cual notificarii de ello a 10s dernh3\nEstados interesados.\nARTICULO XVJ1.- El presente Tratado se celebra por\ntiempo in2eterminado, per0 pcrdra ser denunciado mediante avi-\nso previo de un aiio, transcurrido el cual cesarP en sus efecto!:\npara el Estado denunciante, quedando subsistente para 10s de-\nmit, Estados que Sean parte en 61, por firma o adhesi6n.\nLa denuncia serii dirigida a1 Ministerio de Relaciones Ex-\nteriores y Cultos de 1% Reptiblica Argentina, el cuai la transmi-\nt i r i a 10s demas Estadm interesados.\n!En testimonio de lo cual 10s Plenipotenciarios respcctivoR\nfirman el Presente Tratacio, en un ejemplar, en 10s idiom- es-\nPafiOl Y POfiUgUb Y le QOna SUs sellos, en Rio d 3 Janeiro, D. F.,\na 10s diez dias del m.es de mtubre de mil nove&nta keinb y\ntres.\nPOR LA REPUBLICA ARGENTINA:\n(L. S.) Carlos Saavedra Lam=,\nMinistro de Relaciones Exteriores y Culto.\nPOR LA REPUBLICA DIE LO3 ESTADOS U N I , D B DEL\nBRASIL :\n(L. S.) Afranio de Me110 Franco,\nMinistro de Relaciones Extericrres.\nFOR LA REPUBLICA DE OHILE: Con las reservas de letras\na , b, c y d del articulo V.\n(L. S.) Marcia1 Mkrtinez de Ferrari,\nE m b a j d o r Extraordinario y Pleniipoteniciario en Rio de\nJaneiro.\nFOR LOS EISTADOS UNtIDOS MIEXLCANOS :\n(L. X.) Alfonso Reyes.\nEmbajador Extraordinario y Pleni,poitenciario en Rio de\nJaneiro.                                                              e\nFOR LA REPUBLICA DEL PARAlGVAY:\n(L. S.) Rogelio Lbarra,\nEnviado Extraordinario y Ministro Plenipotenciario en Rlo\nde Janeiro.\nFOR LA REaPUBLICA ORIENTAL DEL UBUGUAY:\n(L. S.) Juan Carlos Blanco,\nEmbajador Extraordinario y Plelnilpotenciario en Rio de\nJaneiro.\nDada en la Sala de Ses'iones del Palacio &El Senado, en San-\nto Dumingo, Capital de la Rep6blica Dominicana a 10s tres d k a\ndel mes de Julio del aiio mil novecientos treinticuatro, afio 91'\nde la Independencia y '719 de la Restauraci6n.\nEl Presidente,                   t\nMario Fermin Cabral.\nLos Secretaries,\nJose Fermin P k e z .\nJ. M. Lldefonso.\nDada e n la &la de Sesiones de la CQmarade Diputados, en\nla c i u d d de Santo Damingo, Capital de la Rep~iblicaDominica-\nna, a 10s diez y who dbs del mes de Julio del aiio mil novocientos\ntreinticuatro; aiios 9 1 ~ de la Independencia y 71\" de la Restaura-\nci6n.\nEl Presidente,\nMigud Angel Roca.\nLw Secwtarios :\nL. E. Hanriquez Castillo.\nH. A. A. Febles.\nEjiec6tese, oomuniquese y publiquese e n todo el territorio\nde la Repfhlica para su conaci'miento y cumglimiento.\nDADA en el Pahcio del Ejecutivo, en la ciudad de Santo           k\n-13’7-\nr(F\nDomingo, Capital de la Republica Dorninicana, a 10s dieciocho\ndias del mes de Julio del afio mil novecientos treinta y cuatro.\nRAFAEL L. TRUJILLO,\nPresidente de la Republica.\nRefrendado :\nPorfirio Herrera,\nSecretario die Estado de la\nPresidencia.\nRefrendado :\nArturo Logrofio,\nSecretario de Estado de Relaeiones\nExteriores.\nDesignacicin del puente sobre el rio Bani con el nombre de ‘‘Jose T r i i j i h\nVald&”.- G. 0. NO. 4701 del 21 de Julio de 1934.\nEL CONGRESO NACIONAL,\nEn Nombre de la Republica\nNUMERO 723.\nCONSIDBRANDO: Que 10s habitantes de la Comun de Ba-\nni, en su gran mayoria, ban ex,presado el deseo de que el Puente\nqus el Estado proyelcta construir sobre el ria Bani, se denomine\n“PUENTE JOSE TRUJILLO VALDE,S”, en honor del progeni-\ntor del Generalisimo Rafael Leonicias Trujillo Moiina, Bsnefac-\ntor de la Patria y Presidente de la Rqpublica;\nCONSIDERANDO: Que es deseo, igualmente, de 10s muni-\ncipes banilejos, demostrar una vez mas su decidida devoci6n a\n. la persona del Generaiisimo Rafael Leonidas Trujillo Mdina,\nBenefactor de la Patria y Presidente de la Repliblica, a1 glorifi-\n$\ncar el nombre de su honorable progenitor,\nDECLARADA LA URGENCIA\nHA DADO LA SIGUIENTE LEY:"
    },
    {
      "provision_ref": "art1",
      "section": "AUTORIZACION AL PRESIDENTE DE LA REPUBLICA PARA DEPOSITAR EL INSTRUMENTO DE ADHESION DE ESTA AL TRAT...",
      "title": "El puente que sera tendido sabre el rio Bani,",
      "content": "Articulo 1 . - El puente que sera tendido sabre el rio Bani,\nen la Comun de Bani, sera amominado “JOSE TRUJILLO\nVALdDES” en honor a1 sefior Don Jos6 Trujillo Vald&, Hijo\nBenemCrito de Bani, actual Diputado a1 Congreso Nacional POP\nla Provincia de Santo Domingo y progenitor del Generalisimo\nRafael Leonidas Trujillo Molina, Benefactor d s la Patria y Pre-\nsidente de la Republica."
    },
    {
      "provision_ref": "art2",
      "section": "AUTORIZACION AL PRESIDENTE DE LA REPUBLICA PARA DEPOSITAR EL INSTRUMENTO DE ADHESION DE ESTA AL TRAT...",
      "title": "L,a Direccih General del Departamento de",
      "content": "Articulo 2 . - L,a Direccih General del Departamento de\nObras Publicas q u d a encargada de’ la fijaci6n de sendas plalcas\nconmemorativas e n las entradas de1 indicado puente, para ser\naescubiertas a1 pdblico el dia de la inauguracidn de esa gran\nobra de progreso nacional.\nDADA en la Sala cie Sesiones de la C6mara de Diputados,\nd     en $anto Domingo, Capital de la Republica Dominicana, a 10s"
    }
  ],
  "definitions": []
}