{
  "id": "do-ley-537-appropriation-for-the-purchase",
  "type": "statute",
  "title": "APPROPRIATION FOR THE PURCHASE OF PROPERTY IN SANTO DOMINGO CITY, AND FOR THE CONSTRUCTION OF A TWEL...",
  "title_en": "APPROPRIATION FOR THE PURCHASE OF PROPERTY IN SANTO DOMINGO CITY, AND FOR THE CONSTRUCTION OF A TWEL...",
  "short_name": "Ley No. 537",
  "status": "in_force",
  "issued_date": "1920-09-03",
  "in_force_date": "1920-09-03",
  "url": "https://www.consultoria.gov.do/Consulta/Home/FileManagement?documentId=3361797&managementType=1",
  "provisions": [
    {
      "provision_ref": "full-text",
      "section": "APPROPRIATION FOR THE PURCHASE OF PROPERTY IN SANTO DOMINGO CITY, AND FOR THE CONSTRUCTION OF A TWEL...",
      "title": "APPROPRIATION FOR THE PURCHASE OF PROPERTY IN SANTO DOMINGO CITY, AND FOR THE CONSTRUCTION OF A TWEL...",
      "content": "-689-\n\n                      ( E . 0 . 536 omitted).\n                        Ss? Spanish text.\n\n     MILITARY GOVERNMENT OF SANTO DOMINGO.\n               Executive Older No. 537.\n\n        Title:    Rppropriztion for the purchase of\n                  property in Santo Doniingo City, and\n                  for the construction of a twelve-roam\n                  schoolhouse thereon.\n    By vixtuc clf the powers vested in the Military Government\nof Santo Doming3, the fcllowirlrg Order is hereby dictate? and\npromulgated :\n    There is hereby appropriated from any funds in the National\nTreasury not otherwise appropriated, the sum of ONE\nH U N D R E D AXD TWENTY-EIGHT THOUSAND DOLLARS\n($128,000.00) for the purchase of property and the erection of\na twelve-room schoolhouse a t Santo Domingo City.\n\n                                   THOMAS SNOWDEN,\n                                 Rear-Admiral, U . S. Navy,\n                           Military Governvr of Santo Domingo.\nSanto Domingo City, D.) R . ,\n    September 3, 1920.\n\n     MILITARY GOVERNMENT OF SANTO DOMINGO.\n               Executive Order No. 538.\n\n        Title:     Endowment for the widow and children of the\n                 late Seiior Licenciado Luis Galvan.\n    WHEREAS the late Sefior Licenciado Luis Galvan died in\nWashington, D. C . , while at his post as Envoy Extraordinary\nand Minister Plenipontentiary of the Dominican Republic t o the\nGovernment of the United States of America, and\n    WHEREAS the late Seiior Licenciado Luis Galvan had spent\nmany years in the Diplcrmttic Serviee of the Republic and was\nat the time of his death performing services of great value. t o\nthe Republic with the zeal and patriotism which merits the\nthanks of the Republic, and\n\n                            -690-\n\n     WHEREAS the widow and children of the deceased ar6 in\ndestitute circumstances and without adequate means of s u p\nport,\n                                                                  *\n      NOW THEREFORE, by virtue of the powers vested in the\n Military Government of Santo Domingo, the following Order is\nhereby dictated and promulgated :\n      Seiiora Carmen Alfau Viuda GalvBn, widow of the late Se-\niior Lufs Ga'lvBn ,is hereby granted a monthly endowment of\n$95.00 during her widowhood, for the purpose of assisting h e r\nto maintain herself and educate her children. .\n    This endowment shall become affective with the month of\nSeptember, 1920, and shall be paid a6 follows:\n    The sum of $380.00 for the lmonths of September, October,\nNovember and December, 1920, shall be payable immediately in\nadvance. From and after January 1, 1921, this endowent shall\nbe paid quarterly in advance.\n    The sum of $380.00 is hereby appropriated from any funds\nin the National Treasury not otherwise appropriated, for the\npayment of this endowment during the year 1920.\n                                  THOMAS SNOWDEN,             4\n                                Rear-Admiral, U . S. Navy,\n                          Military Governor of Santo Domingo.\nh n t o Dorningo City, D, R .,\n      September 4, 1920.\n\n     MILITARY GOVERNMENT OF SANTO DOMINGO.\n               Executive Order No. 539.\n\n        Title : Appropriation to cover purchase of equipment,\n                supplies and salaries in connection with the\n                surveys to be performed under Executive\n                Order 511.\n    By virtue of t h e powers vested in the Military Government\nof Santo Domingo, the following Order is hereby dictated and\npromulgated :\n    There is hereby appropriated from funds now in the National\nTreasury not otherwise appropriated, the sum of SIXTY\nTHOUSAND DOLLARS ($60,000) to cover expenses of purchas-\ning equipment, supplies and payment of salaries in connection\nwith the surveys to be performed under the Law for registration"
    }
  ],
  "definitions": []
}