{
  "id": "do-ley-595-aumento-del-impuesto-adicional",
  "type": "statute",
  "title": "AUMENTO DEL IMPUESTO ADICIONAL EXTRAORDINARIO SOBRE EL ARROZ ESTABLECIDO POR LA LEY NO. 440.",
  "title_en": "AUMENTO DEL IMPUESTO ADICIONAL EXTRAORDINARIO SOBRE EL ARROZ ESTABLECIDO POR LA LEY NO. 440.",
  "short_name": "Ley No. 595",
  "status": "in_force",
  "issued_date": "1933-11-02",
  "in_force_date": "1933-11-02",
  "url": "https://www.consultoria.gov.do/Consulta/Home/FileManagement?documentId=3270213&managementType=1",
  "provisions": [
    {
      "provision_ref": "full-text",
      "section": "AUMENTO DEL IMPUESTO ADICIONAL EXTRAORDINARIO SOBRE EL ARROZ ESTABLECIDO POR LA LEY NO. 440.",
      "title": "AUMENTO DEL IMPUESTO ADICIONAL EXTRAORDINARIO SOBRE EL ARROZ ESTABLECIDO POR LA LEY NO. 440.",
      "content": "-346\n     .\\urnento del impnesto adicional erttaordinatio sobre el armz establecido\n          por la ley No. 440.- G. 0. No. 4623, del 4 de Noviembre de 1933.\n                        EL C O N G R W NACIONAL,\n                         En Nombre de la RepGblica.\n                     HA IjADC, L A S?jGUI.ENTF:LEY:\n     NUMERO 595.\n           ARTICULO UNBtCO:-- Se aumenta a un peso con setenti-\n     cinco centavos or0 americano ($1.75) por ea& C(IJ3N (100) Ki-\n     los Netos, el impuesto adicional extraortiinario cstablecido por la\n     Ley No. 440 sobi-e arroz que se import,? de procedencia extranje-\n     ra.\n           GADA en la Sala de Sesiones de la Ghmara de Diputados, de\n     b ciudad de Santiago de 10s Caballeros, asiento provisional del\n     Yoder Legislativo, a 10streinta dias dzl me9 de Oct&we del aiio\n     mil novecientos treinta y ens, aiios W de la Independencia 71'\n     tie la Restauraciijn.\n                                             Dr. Juan Bta. Ruiz,\n     Los Secretarios :              Diputdo en funciones .de Presidenbe.\n           M. A. Felib.\n           L. E. Henriqwz Castillo.\n           DADA en la Sala de Sesiones del Senado, en k ciudad de\n     Santiago de 10s Caballeros, asiento awiOd.enta1 del P&r ,Legis-\n     lativo, a 10s twintibn bias dzl mes de 4ktubre del aiio mil nove-\n4)   eientos treinta y t r s , aiios 900 de la Independencia y 71q de la\n     Restauracih.\n                                                El Presidknte,\n     Los Secretarios :                     Mario Fermin Cabral.\n           )D. A. ROdTigW.\n           Dr. Lorenzo E Bra.\n           Ejecutese, comuniqmese y publiquese en todo el territorio\n     de la Repbblica, para su conocimientio y cumplimiento.\n           DADA en la ciudad de Santiago de bs Caballeros, R.esidkn-\n     cia temporal del Pocilzr Ejecutivo, a los &s (2)d k s del RES de\n     Noviembra del aiio mil nowcientoa treinta y tres.\n                                    BAFAElL L. TRUJI;LU),\n                                   Presidente de la Rephblica.\n     Refrendado :\n          Jacinto B. Peynado,\n     Secretario cde Estado de la\n             Presidencia.\n                                              'Refpendaclo:\n                                               Nicolk >Vega,\n                               Sub-Secretario, Encargado interinamente\n                                de la Secretaria de Estado de Hacienda.\n     Refrendado :\n              @sar Tolentino,\nd\n     Secretario de E;etado de Agricultura\n                y Cmrcio."
    }
  ],
  "definitions": []
}